keble_documents_loader/__init__.py
keble_documents_loader/html_loader/__init__.py
keble_documents_loader/html_loader/main.py
keble_documents_loader/html_loader/tag.py
keble_documents_loader/html_loader/utils.py
keble_documents_loader/image_loader/__init__.py
keble_documents_loader/image_loader/main.py
keble_documents_loader/wechat_history_loader/__init__.py
keble_documents_loader/wechat_history_loader/main.py
keble_documents_loader-0.0.22.dist-info/METADATA
keble_documents_loader-0.0.22.dist-info/WHEEL
keble_documents_loader-0.0.22.dist-info/RECORD
